krms
