Metadata-Version: 1.1
Name: krms
Version: 0.0.2
Summary: K-RMS unsupervised clustering algorithm.
Home-page: https://github.com/garain/krms
Author: Avishek Garain
Author-email: avishekgarain@gmail.com
License: MIT
Keywords: clustering visualize semisupervised
Platform: UNKNOWN
Classifier: Development Status :: 4 - Beta
Classifier: Intended Audience :: Developers
Classifier: Topic :: Internet
Classifier: License :: OSI Approved :: MIT License
Classifier: Programming Language :: Python
Classifier: Programming Language :: Python :: 2
Classifier: Programming Language :: Python :: 2.6
Classifier: Programming Language :: Python :: 2.7
Classifier: Programming Language :: Python :: 3
Classifier: Programming Language :: Python :: 3.3
Classifier: Programming Language :: Python :: 3.4
Classifier: Programming Language :: Python :: 3.5
